{
	"nome": "João Carlos",
	"ano": "2016/1",
	"regime": "40",
	"dataInicio":"01/01/2016",
	"dataFim":"01/07/2016",
	"notaAvaliacaoDiscente":"9.0",
	"afastamentos":"0",
	"totalMeses": "10",
	"dias":"300",
	"numeroMeses": "10",
	"meses24": "24",
	"somaPonderada": "80",
	"notaCad": "8",
	"notaFinal": "8.0",
	"inciso1": "1",
	"inciso2": "1",
	"inciso3": "1",
	"inciso4": "1",
	"mediaDiscente": "6",
	"mediaProducaoIntelectual": "25",
	"mediaEnsino": "82",
	"mediaEnsinoGraduacao": "40",
	"aprovadoChefia": "1",
	"notaChefia":"5",
	"inciso6": "1",
	"habilitacaoParcial": "1",
	"habilitacaoEstagio": "0",
	"estagioPosdoutoralOuSenior":"0",
	"habilitacaoCargoOuPos": "1",
	"cargoDeDirecao":"0",
	"posGraduando":"0",
	"habilitado": "1",
	"somaEnsino": "40",
	"somaPesquisa": "25",
	"somaAdministracao": "6",
	"somaOutras": "5",
	"S": "76"
}
